yoke/__init__.py
yoke/build_deps.py
yoke/config.py
yoke/deploy.py
yoke/shell.py
yoke/templates.py
yoke/utils.py
yoke-0.12.0.dist-info/LICENSE.txt
yoke-0.12.0.dist-info/METADATA
yoke-0.12.0.dist-info/RECORD
yoke-0.12.0.dist-info/WHEEL
yoke-0.12.0.dist-info/entry_points.txt
yoke-0.12.0.dist-info/top_level.txt
