Metadata-Version: 2.1
Name: yoke
Version: 0.12.0
Summary: AWS Lambda + API Gateway Deployer
Home-page: https://github.com/rackerlabs/yoke
Author: Rackers
Maintainer-email: ryan.walker@rackspace.com
License: Type license() to see the full license text
Keywords: aws lambda apigateway
Platform: UNKNOWN
Classifier: Programming Language :: Python :: 2.7
Classifier: Programming Language :: Python :: 3.6
Requires-Dist: boto3 (>=1.4.2)
Requires-Dist: botocore (>=1.4.85)
Requires-Dist: docker (>=2.0.0)
Requires-Dist: Jinja2 (>=2.8)
Requires-Dist: jsonref (>=0.1)
Requires-Dist: lambda-uploader (>=1.2.0)
Requires-Dist: retrying (>=1.3.3)
Requires-Dist: ruamel.yaml (>=0.11.11)
Requires-Dist: six (>=1.10.0)
